LICENSE
yarndevtools/.gitignore
yarndevtools/__init__.py
yarndevtools/argparser.py
yarndevtools/cdsw/.gitignore
yarndevtools/cdsw/Dockerfile
yarndevtools/cdsw/__init__.py
yarndevtools/cdsw/cdsw_common.py
yarndevtools/cdsw/constants.py
yarndevtools/cdsw/job_configs/__init__.py
yarndevtools/cdsw/job_configs/branch_comparator_job_config.py
yarndevtools/cdsw/job_configs/jira_umbrella_data_fetcher_job_config.py
yarndevtools/cdsw/job_configs/review_sheet_backport_updater_job_config.py
yarndevtools/cdsw/job_configs/reviewsync_job_config.py
yarndevtools/cdsw/job_configs/unit_test_result_aggregator_email_job_config.py
yarndevtools/cdsw/job_configs/unit_test_result_fetcher_job_config.py
yarndevtools/cdsw/launcher_impl.py
yarndevtools/cdsw/resources/cdsw_stacktrace_example.txt
yarndevtools/cdsw/scripts/clone_downstream_repos.sh
yarndevtools/cdsw/scripts/clone_upstream_repos.sh
yarndevtools/cdsw/scripts/experiments/clone_repos_python2.sh
yarndevtools/cdsw/scripts/experiments/exit-test.py
yarndevtools/cdsw/scripts/experiments/exit-test2.py
yarndevtools/cdsw/scripts/experiments/test.py
yarndevtools/cdsw/scripts/experiments/test.sh
yarndevtools/cdsw/scripts/initial-cdsw-setup.sh
yarndevtools/cdsw/scripts/install-requirements.sh
yarndevtools/cdsw/start_job.py
yarndevtools/cdsw/unit-test-result-aggregator/skip_aggregation_defaults.txt
yarndevtools/cdsw_compat.py
yarndevtools/commands/__init__.py
yarndevtools/commands/backporter.py
yarndevtools/commands/branchcomparator/__init__.py
yarndevtools/commands/branchcomparator/branch_comparator.py
yarndevtools/commands/branchcomparator/common.py
yarndevtools/commands/branchcomparator/common_representation.py
yarndevtools/commands/branchcomparator/group_matching.py
yarndevtools/commands/branchcomparator/legacy_script.py
yarndevtools/commands/branchcomparator/simple_matching.py
yarndevtools/commands/format_patch_saver.py
yarndevtools/commands/patch_saver.py
yarndevtools/commands/review_branch_creator.py
yarn_dev_tools-2.0.13.dist-info/LICENSE
yarn_dev_tools-2.0.13.dist-info/METADATA
yarn_dev_tools-2.0.13.dist-info/WHEEL
yarn_dev_tools-2.0.13.dist-info/entry_points.txt
yarn_dev_tools-2.0.13.dist-info/RECORD
