Metadata-Version: 2.1
Name: yarn-dev-tools
Version: 2.0.13
Summary: 
Home-page: https://github.com/szilard-nemeth/yarn-dev-tools
Keywords: YARN,development,dev environment
Author: Szilard Nemeth
Author-email: szilard.nemeth88@gmail.com
Requires-Python: >=3.8.12,<4.0.0
Classifier: Programming Language :: Python :: 3
Classifier: Programming Language :: Python :: 3.9
Classifier: Programming Language :: Python :: 3.10
Classifier: Programming Language :: Python :: 3.11
Classifier: Programming Language :: Python :: 3.12
Requires-Dist: bs4
Requires-Dist: cdsw-job-launcher (==1.0.21)
Requires-Dist: dacite
Requires-Dist: dataclasses-json
Requires-Dist: gitpython
Requires-Dist: google-api-wrapper2 (>=1.0.14,<2.0.0)
Requires-Dist: humanize
Requires-Dist: jira
Requires-Dist: marshmallow
Requires-Dist: pymongo
Requires-Dist: python-common-lib (>=1.0.13,<2.0.0)
Project-URL: Repository, https://github.com/szilard-nemeth/yarn-dev-tools
